{
  "reviewer": "reviewer-21",
  "group_index": 21,
  "law_count": 10,
  "output_path": "audit/review/review-21.json",
  "laws": [
    {
      "law_id": "PL-029-208",
      "public_law": "29-208",
      "title": "Public Law 29-208 | Foreign Affairs Accountability Act",
      "report_path": "audit/primary/batch-07-03.json",
      "batch": 7,
      "source_status": "current",
      "validation_status": "missing chronology analysis",
      "confidence": "high",
      "reasons": [
        "direct-action-provision",
        "standalone-permanent-provision"
      ],
      "provision_refs": [
        "SEC3(a)",
        "SEC3(b)",
        "SEC3(c)"
      ],
      "targets": [
        "Public Law 15-102, Section IV"
      ]
    },
    {
      "law_id": "PL-029-210",
      "public_law": "29-210",
      "title": "Public Law 29-210 | Military Justice Reform Act of 2024",
      "report_path": "audit/primary/batch-07-03.json",
      "batch": 7,
      "source_status": "current",
      "validation_status": "missing chronology analysis",
      "confidence": "high",
      "reasons": [
        "direct-action-provision",
        "standalone-permanent-provision"
      ],
      "provision_refs": [
        "SEC3(a)",
        "SEC4(b)",
        "SEC5",
        "SEC6",
        "SEC7",
        "SEC8(a)-(v)"
      ],
      "targets": [
        "/us/usc/t10/s807; /us/usc/t10/s825; /us/usc/t10/s832; /us/usc/t10/s839; /us/usc/t10/s845",
        "Public Laws 15-104, 19-146"
      ]
    },
    {
      "law_id": "PL-029-211",
      "public_law": "29-211",
      "title": "Public Law 29-211 | Amendment to the Presidential Succession Act of 1947",
      "report_path": "audit/primary/batch-08-01.json",
      "batch": 8,
      "source_status": "current",
      "validation_status": "missing chronology analysis",
      "confidence": "high",
      "reasons": [
        "direct-action-provision",
        "multiple-laws-same-target"
      ],
      "provision_refs": [
        "SEC. 3(a)(i)",
        "SEC. 3(a)(ii)-(iii)",
        "SEC. 3(a)(iv)"
      ],
      "targets": [
        "/us/usc/t3/s1",
        "/us/usc/t3/s19"
      ]
    },
    {
      "law_id": "PL-029-213",
      "public_law": "29-213",
      "title": "Public Law 29-213 | D.C Delegate Elimination Act",
      "report_path": "audit/primary/batch-08-01.json",
      "batch": 8,
      "source_status": "fully-repealed",
      "validation_status": "missing chronology analysis",
      "confidence": "high",
      "reasons": [
        "direct-action-provision",
        "status:fully-repealed"
      ],
      "provision_refs": [
        "SECTION II"
      ],
      "targets": [
        "/us/usc/t2/s1",
        "Public Law 16-120 ? 4"
      ]
    },
    {
      "law_id": "PL-029-214",
      "public_law": "29-214",
      "title": "Public Law 29-214 | Safeguarding American Democracy and Maintaining Order in our Streets Act",
      "report_path": "audit/primary/batch-08-01.json",
      "batch": 8,
      "source_status": "current",
      "validation_status": "unsupported",
      "confidence": "high",
      "reasons": [
        "standalone-permanent-provision"
      ],
      "provision_refs": [
        "SECTION III"
      ],
      "targets": [
        "/us/usc/t50/s1"
      ]
    },
    {
      "law_id": "PL-029-215",
      "public_law": "29-215",
      "title": "Public Law 29-215 | Stability in the Presidency Act",
      "report_path": "audit/primary/batch-08-01.json",
      "batch": 8,
      "source_status": "current",
      "validation_status": "missing chronology analysis",
      "confidence": "high",
      "reasons": [
        "direct-action-provision",
        "multiple-laws-same-target"
      ],
      "provision_refs": [
        "SEC. 4",
        "SEC. 4(g)-(h)"
      ],
      "targets": [
        "/us/usc/t3/s1",
        "/us/usc/t3/s19"
      ]
    },
    {
      "law_id": "PL-029-216",
      "public_law": "29-216",
      "title": "Public Law 29-216 | District of Columbia Home Rule Act of 2025",
      "report_path": "audit/primary/batch-08-01.json",
      "batch": 8,
      "source_status": "fully-repealed",
      "validation_status": "missing chronology analysis",
      "confidence": "high",
      "reasons": [
        "direct-action-provision",
        "status:fully-repealed"
      ],
      "provision_refs": [
        "TITLE III / SEC. 321-322",
        "TITLE V / SEC. 501-506"
      ],
      "targets": [
        "/us/usc/t40/s101/4"
      ]
    },
    {
      "law_id": "PL-029-217",
      "public_law": "29-217",
      "title": "Public Law 29-217 | Private Regulations and Compliance Act",
      "report_path": "audit/primary/batch-08-01.json",
      "batch": 8,
      "source_status": "current",
      "validation_status": "missing chronology analysis",
      "confidence": "high",
      "reasons": [
        "direct-action-provision",
        "standalone-permanent-provision"
      ],
      "provision_refs": [
        "SECTION II",
        "SECTION IV"
      ],
      "targets": [
        "/us/usc/t15/s1",
        "Public Law 4-27"
      ]
    },
    {
      "law_id": "PL-029-218",
      "public_law": "29-218",
      "title": "Public Law 29-218 | Public Officials Security Act",
      "report_path": "audit/primary/batch-08-01.json",
      "batch": 8,
      "source_status": "current",
      "validation_status": "accepted with corrections",
      "confidence": "high",
      "reasons": [
        "standalone-permanent-provision"
      ],
      "provision_refs": [
        "SECTION II"
      ],
      "targets": [
        "/us/usc/t50/s1"
      ]
    },
    {
      "law_id": "PL-030-220",
      "public_law": "30-220",
      "title": "Public Law 30-220 | Supreme Court Justice Allotment Act",
      "report_path": "audit/primary/batch-08-01.json",
      "batch": 8,
      "source_status": "current",
      "validation_status": "missing chronology analysis",
      "confidence": "high",
      "reasons": [
        "standalone-permanent-provision"
      ],
      "provision_refs": [
        "SEC. 3"
      ],
      "targets": [
        "/us/usc/t28/s1"
      ]
    }
  ]
}
