{
  "reviewer": "review-repair-07",
  "group_index": 107,
  "law_count": 10,
  "output_path": "audit/review/review-07.json",
  "laws": [
    {
      "law_id": "PL-009-062",
      "public_law": "9-62",
      "title": "Public Law 9-62 | Repealing the District of Columbia Home Rule Act",
      "primary_report_path": "audit/primary/batch-03-01.json",
      "source_review_path": "audit/review/review-07.json",
      "source_status": "current",
      "validation_status": "accepted with corrections"
    },
    {
      "law_id": "PL-009-063",
      "public_law": "9-63",
      "title": "Public Law 9-63 | The Federal District Employment Act of 2022",
      "primary_report_path": "audit/primary/batch-03-01.json",
      "source_review_path": "audit/review/review-07.json",
      "source_status": "unresolved",
      "validation_status": "unsupported"
    },
    {
      "law_id": "PL-010-065",
      "public_law": "10-65",
      "title": "Public Law 10-65 | Federal Judicial Reform Act ii",
      "primary_report_path": "audit/primary/batch-03-01.json",
      "source_review_path": "audit/review/review-07.json",
      "source_status": "fully-repealed",
      "validation_status": "missing chronology analysis"
    },
    {
      "law_id": "PL-010-066",
      "public_law": "10-66",
      "title": "Public Law 10-66 | The Americans First Act",
      "primary_report_path": "audit/primary/batch-03-01.json",
      "source_review_path": "audit/review/review-07.json",
      "source_status": "current",
      "validation_status": "accepted with corrections"
    },
    {
      "law_id": "PL-010-067",
      "public_law": "10-67",
      "title": "Public Law 10-67 | Ambassadorial Readjustment Act",
      "primary_report_path": "audit/primary/batch-03-01.json",
      "source_review_path": "audit/review/review-07.json",
      "source_status": "current",
      "validation_status": "accepted with corrections"
    },
    {
      "law_id": "PL-010-068",
      "public_law": "10-68",
      "title": "Public Law 10-68 | American Jobs Act",
      "primary_report_path": "audit/primary/batch-03-01.json",
      "source_review_path": "audit/review/review-07.json",
      "source_status": "current",
      "validation_status": "accepted with corrections"
    },
    {
      "law_id": "PL-011-069",
      "public_law": "11-69",
      "title": "Public Law 11-69 | DC Criminal Code Act",
      "primary_report_path": "audit/primary/batch-03-01.json",
      "source_review_path": "audit/review/review-07.json",
      "source_status": "current",
      "validation_status": "accepted with corrections"
    },
    {
      "law_id": "PL-011-070",
      "public_law": "11-70",
      "title": "Public Law 11-70 | Supreme Court Please Act",
      "primary_report_path": "audit/primary/batch-03-01.json",
      "source_review_path": "audit/review/review-07.json",
      "source_status": "current",
      "validation_status": "missing chronology analysis"
    },
    {
      "law_id": "PL-011-071",
      "public_law": "11-71",
      "title": "Public Law 11-71 | Supreme Court Needs Act",
      "primary_report_path": "audit/primary/batch-03-02.json",
      "source_review_path": "audit/review/review-07.json",
      "source_status": "current",
      "validation_status": "missing chronology analysis"
    },
    {
      "law_id": "PL-011-072",
      "public_law": "11-72",
      "title": "Public Law 11-72 | No More Mariah Act",
      "primary_report_path": "audit/primary/batch-03-02.json",
      "source_review_path": "audit/review/review-07.json",
      "source_status": "current",
      "validation_status": "missing chronology analysis"
    }
  ]
}
