{
  "reviewer": "review-repair-69",
  "group_index": 169,
  "law_count": 10,
  "output_path": "audit/review/review-repair-69.json",
  "source_review_path": "audit/review/review-69.json",
  "laws": [
    {
      "law_id": "PL-023-172",
      "public_law": "23-172",
      "title": "Public Law 23-172 | Congressional Military Service Act",
      "source_review_path": "audit/review/review-69.json",
      "validation_status": "repealed"
    },
    {
      "law_id": "PL-024-173",
      "public_law": "24-173",
      "title": "Public Law 24-173 | Federal Enhancement Against Foreign Intrusion Act",
      "source_review_path": "audit/review/review-69.json",
      "validation_status": "active"
    },
    {
      "law_id": "PL-024-174",
      "public_law": "24-174",
      "title": "Public Law 24-174 | Washington, D.C. Permitless Carry Act",
      "source_review_path": "audit/review/review-69.json",
      "validation_status": "repealed"
    },
    {
      "law_id": "PL-024-175",
      "public_law": "24-175",
      "title": "Public Law 24-175 | MPD Relocation Act",
      "source_review_path": "audit/review/review-69.json",
      "validation_status": "unresolved"
    },
    {
      "law_id": "PL-024-176",
      "public_law": "24-176",
      "title": "Public Law 24-176 | Comprehensive Federal Government Funding Act",
      "source_review_path": "audit/review/review-69.json",
      "validation_status": "unresolved"
    },
    {
      "law_id": "PL-024-177",
      "public_law": "24-177",
      "title": "Public Law 24-177 | SS Jurisdiction Act",
      "source_review_path": "audit/review/review-69.json",
      "validation_status": "repealed"
    },
    {
      "law_id": "PL-024-178",
      "public_law": "24-178",
      "title": "Public Law 24-178 | Equality in Employment Act",
      "source_review_path": "audit/review/review-69.json",
      "validation_status": "active"
    },
    {
      "law_id": "PL-025-179",
      "public_law": "25-179",
      "title": "Public Law 25-179 | Fiscal Year 21-2",
      "source_review_path": "audit/review/review-69.json",
      "validation_status": "active"
    },
    {
      "law_id": "PL-025-180",
      "public_law": "25-180",
      "title": "Public Law 25-180 | Sanction Repealment Act",
      "source_review_path": "audit/review/review-69.json",
      "validation_status": "repealed"
    },
    {
      "law_id": "PL-025-181",
      "public_law": "25-181",
      "title": "Public Law 25-181 | Federal District of Columbia Criminal Code",
      "source_review_path": "audit/review/review-69.json",
      "validation_status": "repealed"
    }
  ]
}
